autoversion_pbr/__init__.py
autoversion_pbr-0.1.2.dist-info/DESCRIPTION.rst
autoversion_pbr-0.1.2.dist-info/METADATA
autoversion_pbr-0.1.2.dist-info/RECORD
autoversion_pbr-0.1.2.dist-info/WHEEL
autoversion_pbr-0.1.2.dist-info/entry_points.txt
autoversion_pbr-0.1.2.dist-info/metadata.json
autoversion_pbr-0.1.2.dist-info/pbr.json
autoversion_pbr-0.1.2.dist-info/top_level.txt
