Metadata-Version: 2.0
Name: autoversion-pbr
Version: 0.1.2
Summary: UNKNOWN
Home-page: UNKNOWN
Author: Michael Tharp
Author-email: michael.tharp@sas.com
License: UNKNOWN
Platform: UNKNOWN
Classifier: Development Status :: 4 - Beta
Classifier: Intended Audience :: Developers
Classifier: Intended Audience :: Information Technology
Classifier: License :: OSI Approved :: Apache Software License
Classifier: Operating System :: Microsoft :: Windows
Classifier: Operating System :: Unix
Classifier: Programming Language :: Python :: 2.7
Classifier: Programming Language :: Python :: 3.4
Classifier: Programming Language :: Python :: 3.5
Classifier: Topic :: Software Development :: Build Tools
Classifier: Topic :: System :: Archiving :: Packaging
Requires-Dist: packaging
Requires-Dist: pbr
